mcp_pinecone/__init__.py
mcp_pinecone/chunking.py
mcp_pinecone/constants.py
mcp_pinecone/pinecone.py
mcp_pinecone/prompts.py
mcp_pinecone/server.py
mcp_pinecone/tools.py
mcp_pinecone/utils.py
mcp_pinecone-0.1.8.dist-info/METADATA
mcp_pinecone-0.1.8.dist-info/WHEEL
mcp_pinecone-0.1.8.dist-info/entry_points.txt
mcp_pinecone-0.1.8.dist-info/licenses/LICENSE
mcp_pinecone-0.1.8.dist-info/RECORD
