Metadata-Version: 2.4
Name: mcp-pinecone
Version: 0.1.8
Summary: Read and write to Pinecone from Claude Desktop with Model Context Protocol.
Project-URL: Homepage, https://sirmews.github.io/mcp-pinecone/
Project-URL: Issues, https://github.com/sirmews/mcp-pinecone/issues
Author-email: Navishkar Rao <nav@perfectlycromulent.dev>
License-File: LICENSE
Classifier: License :: OSI Approved :: MIT License
Classifier: Operating System :: MacOS
Classifier: Programming Language :: Python :: 3
Requires-Python: >=3.12
Requires-Dist: httpx>=0.28.0
Requires-Dist: jsonschema>=4.23.0
Requires-Dist: mcp>=1.0.0
Requires-Dist: pinecone>=5.4.1
Requires-Dist: python-dotenv>=1.0.1
Requires-Dist: tiktoken>=0.8.0
